rhosocial/activerecord/testsuite/__init__.py
rhosocial/activerecord/testsuite/conftest.py
rhosocial/activerecord/testsuite/utils.py
rhosocial/activerecord/testsuite/benchmark/README.md
rhosocial/activerecord/testsuite/core/__init__.py
rhosocial/activerecord/testsuite/core/registry.py
rhosocial/activerecord/testsuite/feature/FEATURE_SUPPORT_DESIGN.md
rhosocial/activerecord/testsuite/feature/FEATURE_SUPPORT_USAGE.md
rhosocial/activerecord/testsuite/feature/MIGRATION_GUIDE.md
rhosocial/activerecord/testsuite/feature/README.md
rhosocial/activerecord/testsuite/feature/features.py
rhosocial/activerecord/testsuite/feature/test_capability_integration.py
rhosocial/activerecord/testsuite/feature/test_features.py
rhosocial/activerecord/testsuite/feature/backend/sqlite_features.py
rhosocial/activerecord/testsuite/feature/basic/conftest.py
rhosocial/activerecord/testsuite/feature/basic/interfaces.py
rhosocial/activerecord/testsuite/feature/basic/test_crud.py
rhosocial/activerecord/testsuite/feature/basic/test_fields.py
rhosocial/activerecord/testsuite/feature/basic/test_validation.py
rhosocial/activerecord/testsuite/feature/basic/fixtures/models.py
rhosocial/activerecord/testsuite/feature/events/conftest.py
rhosocial/activerecord/testsuite/feature/events/interfaces.py
rhosocial/activerecord/testsuite/feature/events/test_handlers.py
rhosocial/activerecord/testsuite/feature/events/test_lifecycle.py
rhosocial/activerecord/testsuite/feature/events/fixtures/models.py
rhosocial/activerecord/testsuite/feature/examples/capability_usage_example.py
rhosocial/activerecord/testsuite/feature/interface/conftest.py
rhosocial/activerecord/testsuite/feature/interface/test_threadsafe_dict.py
rhosocial/activerecord/testsuite/feature/mixins/conftest.py
rhosocial/activerecord/testsuite/feature/mixins/interfaces.py
rhosocial/activerecord/testsuite/feature/mixins/test_combined_articles.py
rhosocial/activerecord/testsuite/feature/mixins/test_optimistic_lock.py
rhosocial_activerecord_testsuite-1.0.0.dev2.dist-info/licenses/LICENSE
rhosocial_activerecord_testsuite-1.0.0.dev2.dist-info/METADATA
rhosocial_activerecord_testsuite-1.0.0.dev2.dist-info/WHEEL
rhosocial_activerecord_testsuite-1.0.0.dev2.dist-info/entry_points.txt
rhosocial_activerecord_testsuite-1.0.0.dev2.dist-info/top_level.txt
rhosocial_activerecord_testsuite-1.0.0.dev2.dist-info/RECORD
