Metadata-Version: 2.4
Name: rhosocial-activerecord-testsuite
Version: 1.0.0.dev2
Summary: A standardized test suite for rhosocial-activerecord backends, providing contracts for features, real-world scenarios, and benchmarks.
Author-email: vistart <i@vistart.me>
License:                                  Apache License
Project-URL: Homepage, https://github.com/rhosocial/python-activerecord-testsuite
Project-URL: Documentation, https://docs.python-activerecord.dev.rho.social/
Project-URL: Repository, https://github.com/rhosocial/python-activerecord-testsuite.git
Project-URL: Issues, https://github.com/rhosocial/python-activerecord-testsuite/issues
Keywords: testsuite,activerecord,orm,database,pytest,rhosocial
Classifier: Development Status :: 3 - Alpha
Classifier: Intended Audience :: Developers
Classifier: License :: OSI Approved :: Apache Software License
Classifier: Programming Language :: Python :: 3
Classifier: Programming Language :: Python :: 3.8
Classifier: Programming Language :: Python :: 3.9
Classifier: Programming Language :: Python :: 3.10
Classifier: Programming Language :: Python :: 3.11
Classifier: Programming Language :: Python :: 3.12
Classifier: Programming Language :: Python :: 3.13
Classifier: Programming Language :: Python :: 3.14
Classifier: Framework :: Pytest
Classifier: Topic :: Software Development :: Testing
Classifier: Topic :: Software Development :: Testing :: Acceptance
Classifier: Topic :: Software Development :: Testing :: BDD
Classifier: Topic :: Software Development :: Testing :: Mocking
Classifier: Topic :: Software Development :: Testing :: Unit
Requires-Python: >=3.8
License-File: LICENSE
Requires-Dist: pytest>=7.0.0
Provides-Extra: test
Requires-Dist: pytest-asyncio>=0.21.0; extra == "test"
Requires-Dist: pytest-cov>=4.0.0; extra == "test"
Requires-Dist: pytest-xdist>=3.6.1; extra == "test"
Requires-Dist: pytest-rerunfailures>=15.0; extra == "test"
Provides-Extra: dev
Requires-Dist: towncrier>=23.0.0; extra == "dev"
Requires-Dist: black>=23.0.0; extra == "dev"
Requires-Dist: isort>=5.0.0; extra == "dev"
Requires-Dist: mypy>=1.0.0; extra == "dev"
Requires-Dist: ruff>=0.1.0; extra == "dev"
Requires-Dist: pre-commit>=3.0.0; extra == "dev"
Provides-Extra: docs
Requires-Dist: sphinx>=7.0.0; extra == "docs"
Requires-Dist: sphinx-rtd-theme>=1.0.0; extra == "docs"
Requires-Dist: myst-parser>=2.0.0; extra == "docs"
Dynamic: license-file
